astmaxxx/__init__.py
astmaxxx/__main__.py
astmaxxx-0.1.0.dist-info/METADATA
astmaxxx-0.1.0.dist-info/WHEEL
astmaxxx-0.1.0.dist-info/top_level.txt
astmaxxx-0.1.0.dist-info/RECORD
