Metadata-Version: 2.1
Name: astmaxxx
Version: 0.1.0
Summary: astma codes
Home-page: https://github.com/HV4512/astma_codes
Author: Harsh Vardhan
Author-email: jobbykarn@gmail.com
License: Open-Source
